{
	"id": "8WH6sOX5G9EI8Cg",
	"json": "{\"id\":\"8WH6sOX5G9EI8Cg\",\"url\":\"https://www.iana.org/domains/root/db/xn--mgbgu82a.html\",\"uniqueKey\":\"https://www.iana.org/domains/root/db/xn--mgbgu82a.html\",\"method\":\"GET\",\"noRetry\":false,\"retryCount\":0,\"errorMessages\":[],\"headers\":{},\"userData\":{\"depth\":2}}",
	"method": "GET",
	"orderNo": 1691664436975,
	"retryCount": 0,
	"uniqueKey": "https://www.iana.org/domains/root/db/xn--mgbgu82a.html",
	"url": "https://www.iana.org/domains/root/db/xn--mgbgu82a.html"
}