{
	"id": "eI6C5j2I34itufi",
	"json": "{\"id\":\"eI6C5j2I34itufi\",\"url\":\"https://www.iana.org/domains/root/db/xn--90ae.html\",\"uniqueKey\":\"https://www.iana.org/domains/root/db/xn--90ae.html\",\"method\":\"GET\",\"noRetry\":false,\"retryCount\":0,\"errorMessages\":[],\"headers\":{},\"userData\":{\"depth\":2}}",
	"method": "GET",
	"orderNo": 1691664436928,
	"retryCount": 0,
	"uniqueKey": "https://www.iana.org/domains/root/db/xn--90ae.html",
	"url": "https://www.iana.org/domains/root/db/xn--90ae.html"
}