{
	"id": "w5aJLUnI147ctrd",
	"json": "{\"id\":\"w5aJLUnI147ctrd\",\"url\":\"https://www.iana.org/domains/root/db/alsace.html\",\"uniqueKey\":\"https://www.iana.org/domains/root/db/alsace.html\",\"method\":\"GET\",\"noRetry\":false,\"retryCount\":0,\"errorMessages\":[],\"headers\":{},\"userData\":{\"depth\":2}}",
	"method": "GET",
	"orderNo": 1691664436347,
	"retryCount": 0,
	"uniqueKey": "https://www.iana.org/domains/root/db/alsace.html",
	"url": "https://www.iana.org/domains/root/db/alsace.html"
}