{
	"id": "Lnk4awqJotkwTkD",
	"json": "{\"id\":\"Lnk4awqJotkwTkD\",\"url\":\"https://rbi.org.in/scripts/FS_Notification.aspx?fn=5\",\"uniqueKey\":\"https://rbi.org.in/scripts/FS_Notification.aspx?fn=5\",\"method\":\"GET\",\"noRetry\":false,\"retryCount\":0,\"errorMessages\":[],\"headers\":{},\"userData\":{\"depth\":1}}",
	"method": "GET",
	"orderNo": 1691664869538,
	"retryCount": 0,
	"uniqueKey": "https://rbi.org.in/scripts/FS_Notification.aspx?fn=5",
	"url": "https://rbi.org.in/scripts/FS_Notification.aspx?fn=5"
}